electrumsv_secp256k1/_libsecp256k1.cpython-39-x86_64-linux-gnu.so
electrumsv_secp256k1/_windows_libsecp256k1.py
electrumsv_secp256k1/py.typed
electrumsv_secp256k1/__init__.py
electrumsv_secp256k1-18.0.0.dist-info/LICENSE-MIT
electrumsv_secp256k1-18.0.0.dist-info/top_level.txt
electrumsv_secp256k1-18.0.0.dist-info/RECORD
electrumsv_secp256k1-18.0.0.dist-info/METADATA
electrumsv_secp256k1-18.0.0.dist-info/WHEEL
electrumsv_secp256k1-18.0.0.dist-info/LICENSE-APACHE
