Metadata-Version: 2.1
Name: electrumsv-secp256k1
Version: 18.0.0
Summary: Cross-platform Python CFFI bindings for libsecp256k1
Home-page: UNKNOWN
Author-email: Roger Taylor <roger.taylor.email@gmail.com>
License: MIT OR Apache-2.0
Project-URL: Documentation, https://ofek.dev/coincurve/
Project-URL: Issues, https://github.com/ofek/coincurve/issues
Project-URL: Source, https://github.com/ofek/coincurve
Keywords: secp256k1,crypto,elliptic curves,bitcoin,ethereum,cryptocurrency
Platform: UNKNOWN
Classifier: Development Status :: 5 - Production/Stable
Classifier: Intended Audience :: Developers
Classifier: License :: OSI Approved :: MIT License
Classifier: License :: OSI Approved :: Apache Software License
Classifier: Natural Language :: English
Classifier: Operating System :: OS Independent
Classifier: Programming Language :: Python :: 3
Classifier: Programming Language :: Python :: 3.7
Classifier: Programming Language :: Python :: 3.8
Classifier: Programming Language :: Python :: 3.9
Classifier: Programming Language :: Python :: 3.10
Classifier: Programming Language :: Python :: 3.11
Classifier: Programming Language :: Python :: Implementation :: CPython
Classifier: Programming Language :: Python :: Implementation :: PyPy
Classifier: Topic :: Software Development :: Libraries
Classifier: Topic :: Security :: Cryptography
Requires-Python: >=3.7
License-File: LICENSE-APACHE
License-File: LICENSE-MIT
